sito_io/__init__.py
sito_io/abc.py
sito_io/errors.py
sito_io/fileio.py
sito_io/manifest.py
sito_io/dctypes/__init__.py
sito_io/dctypes/resource.py
sito_io/pydtypes/__init__.py
sito_io/pydtypes/resource.py
sito_io-0.0.2.dist-info/AUTHORS
sito_io-0.0.2.dist-info/LICENSE
sito_io-0.0.2.dist-info/METADATA
sito_io-0.0.2.dist-info/WHEEL
sito_io-0.0.2.dist-info/pbr.json
sito_io-0.0.2.dist-info/top_level.txt
sito_io-0.0.2.dist-info/RECORD
