Metadata-Version: 2.1
Name: sito-io
Version: 0.0.2
Summary: Standard Interfaces for Object Transformation - File I/O Structures
Home-page: https://github.com/xkortex/sito-io
Author: Michael McDermott
Author-email: michaelmcdermott11@gmail.com
License: MIT
Keywords: setup,distutils
Platform: UNKNOWN
Classifier: Development Status :: 3 - Alpha
Classifier: Environment :: Console
Classifier: Intended Audience :: Developers
Classifier: Intended Audience :: Information Technology
Classifier: License :: OSI Approved :: MIT License
Classifier: Operating System :: POSIX
Classifier: Programming Language :: Python
